django_logging_headers/__init__.py
django_logging_headers/config.py
django_logging_headers/handlers.py
django_logging_headers-0.0.2.dist-info/METADATA
django_logging_headers-0.0.2.dist-info/WHEEL
django_logging_headers-0.0.2.dist-info/entry_points.txt
django_logging_headers-0.0.2.dist-info/top_level.txt
django_logging_headers-0.0.2.dist-info/RECORD
