Metadata-Version: 2.1
Name: django-logging-headers
Version: 0.0.2
Summary: base django you can save headers info to log
Home-page: https://www.cnblogs.com/fuchenjie/p/15187593.html
Author: fcj
Author-email: 709124637@qq.com
License: UNKNOWN
Platform: UNKNOWN
